<?xml version="1.0" encoding="UTF-8" standalone="yes"?>
<unit xmlns="http://www.sdml.info/srcML/src" xmlns:cpp="http://www.sdml.info/srcML/cpp" language="C" filename="subversion/include/svn_md5.h"><cpp:if>#<cpp:directive>if</cpp:directive> <expr>!<call><name>defined</name><argument_list>(<argument><expr><name>SVN_MD5_H</name></expr></argument>)</argument_list></call></expr></cpp:if>
<cpp:define>#<cpp:directive>define</cpp:directive> <cpp:macro><name>SVN_MD5_H</name></cpp:macro></cpp:define>
<cpp:include>#<cpp:directive>include</cpp:directive> <cpp:file>&lt;apr_pools.h&gt;</cpp:file></cpp:include>
<cpp:include>#<cpp:directive>include</cpp:directive> <cpp:file>&lt;apr_md5.h&gt;</cpp:file></cpp:include>
<cpp:include>#<cpp:directive>include</cpp:directive> <cpp:file>"svn_error.h"</cpp:file></cpp:include>
<cpp:include>#<cpp:directive>include</cpp:directive> <cpp:file>"svn_pools.h"</cpp:file></cpp:include>
<cpp:if>#<cpp:directive>if</cpp:directive> <expr><call><name>defined</name><argument_list>(<argument><expr><name>__cplusplus</name></expr></argument>)</argument_list></call></expr></cpp:if>
<extern>extern "C" <block>{
<cpp:endif>#<cpp:directive>endif</cpp:directive></cpp:endif>
<function_decl><type><specifier>const</specifier> <name>unsigned</name> <name>char</name> *</type><name>svn_md5_empty_string_digest</name><parameter_list>(<param><decl><type><name>void</name></type></decl></param>)</parameter_list>;</function_decl>
<function_decl><type><specifier>const</specifier> <name>char</name> *</type><name>svn_md5_digest_to_cstring_display</name><parameter_list>(<param><decl><type><specifier>const</specifier> <name>unsigned</name> <name>char</name></type> <name><name>digest</name><index>[]</index></name></decl></param>,
<param><decl><type><name>apr_pool_t</name> *</type><name>pool</name></decl></param>)</parameter_list>;</function_decl>
<function_decl><type><specifier>const</specifier> <name>char</name> *</type><name>svn_md5_digest_to_cstring</name><parameter_list>(<param><decl><type><specifier>const</specifier> <name>unsigned</name> <name>char</name></type> <name><name>digest</name><index>[]</index></name></decl></param>,
<param><decl><type><name>apr_pool_t</name> *</type><name>pool</name></decl></param>)</parameter_list>;</function_decl>
<function_decl><type><name>svn_boolean_t</name></type> <name>svn_md5_digests_match</name><parameter_list>(<param><decl><type><specifier>const</specifier> <name>unsigned</name> <name>char</name></type> <name><name>d1</name><index>[]</index></name></decl></param>,
<param><decl><type><specifier>const</specifier> <name>unsigned</name> <name>char</name></type> <name><name>d2</name><index>[]</index></name></decl></param>)</parameter_list>;</function_decl>
<cpp:if>#<cpp:directive>if</cpp:directive> <expr><call><name>defined</name><argument_list>(<argument><expr><name>__cplusplus</name></expr></argument>)</argument_list></call></expr></cpp:if>
}</block></extern>
<cpp:endif>#<cpp:directive>endif</cpp:directive></cpp:endif>
<cpp:endif>#<cpp:directive>endif</cpp:directive></cpp:endif>
</unit>
